{
  "author": "",
  "id": "EDA",
  "name": "EDA",
  "naming_scheme": "S{{##}}-{{name}}.{{ext}}",
  "steps": [
    {
      "name": "S01-intro.py",
      "title": "S01-intro.py"
    },
    {
      "name": "S02-sales_chart.py",
      "title": "S02-sales_chart.py"
    },
    {
      "name": "S03-correlations.py",
      "title": "S03-correlations.py"
    },
    {
      "name": "S04-customers.py",
      "title": "S04-customers.py"
    },
    {
      "name": "S05-promo1.py",
      "title": "S05-promo1.py"
    },
    {
      "name": "S06-promo2.py",
      "title": "S06-promo2.py"
    },
    "S07-promo_ANOVA.py",
    "S08-promo2.py",
    "S09-trend.py",
    "S10-day_of_week.py",
    "S11-state_holiday.py",
    "S12-school_holiday.py",
    "S13-assortment_store_type.py"
  ],
  "summary": "",
  "title": "EDA"
}